goad_toolkit/__init__.py
goad_toolkit/analytics.py
goad_toolkit/config.py
goad_toolkit/dataprocessor.py
goad_toolkit/datatransforms.py
goad_toolkit/distributions.py
goad_toolkit/filehandler.py
goad_toolkit/models.py
goad_toolkit/visualizer.py
goad_toolkit-0.1.4.dist-info/METADATA
goad_toolkit-0.1.4.dist-info/WHEEL
goad_toolkit-0.1.4.dist-info/entry_points.txt
goad_toolkit-0.1.4.dist-info/RECORD
