Metadata-Version: 2.4
Name: goad-toolkit
Version: 0.1.4
Summary: An extensible toolkit for Goal Oriented Analysis of Data
Project-URL: Github, https://github.com/raoulg/goad_toolkit
Author-email: raoul grouls <Raoul.Grouls@han.nl>
Requires-Python: >=3.12
Requires-Dist: loguru>=0.7.3
Requires-Dist: matplotlib>=3.10.1
Requires-Dist: numpy>=2.2.4
Requires-Dist: pandas>=2.2.3
Requires-Dist: pydantic>=2.10.6
Requires-Dist: requests>=2.32.3
Requires-Dist: scipy>=1.15.2
Requires-Dist: seaborn>=0.13.2
Requires-Dist: tqdm>=4.67.1
